README.txt
setup.py
collective/__init__.py
collective.nivoslider.egg-info/PKG-INFO
collective.nivoslider.egg-info/SOURCES.txt
collective.nivoslider.egg-info/dependency_links.txt
collective.nivoslider.egg-info/entry_points.txt
collective.nivoslider.egg-info/namespace_packages.txt
collective.nivoslider.egg-info/not-zip-safe
collective.nivoslider.egg-info/paster_plugins.txt
collective.nivoslider.egg-info/requires.txt
collective.nivoslider.egg-info/top_level.txt
collective/nivoslider/__init__.py
collective/nivoslider/configure.zcml
collective/nivoslider/tests.py
collective/nivoslider/browser/__init__.py
collective/nivoslider/browser/configure.zcml
collective/nivoslider/browser/demo.pt
collective/nivoslider/browser/jquery.nivo.slider.js
collective/nivoslider/browser/jquery.nivo.slider.pack.js
collective/nivoslider/browser/license.txt
collective/nivoslider/browser/nivo-slider.css
collective/nivoslider/browser/style.css
collective/nivoslider/browser/images/arrows.png
collective/nivoslider/browser/images/background.png
collective/nivoslider/browser/images/bullets.png
collective/nivoslider/browser/images/dev7logo.png
collective/nivoslider/browser/images/loading.gif
collective/nivoslider/browser/images/nemo.jpg
collective/nivoslider/browser/images/slider.png
collective/nivoslider/browser/images/toystory.jpg
collective/nivoslider/browser/images/up.jpg
collective/nivoslider/browser/images/walle.jpg
collective/nivoslider/profiles/default/cssregistry.xml
collective/nivoslider/profiles/default/jsregistry.xml
collective/nivoslider/profiles/default/metadata.xml
docs/HISTORY.txt
docs/INSTALL.txt
docs/LICENSE.GPL
docs/LICENSE.txt