Metadata-Version: 1.0
Name: collective.nivoslider
Version: 0.1a
Summary: A jQuery plugin that provides the nivoslider from dev7studios.com - a simple slideshow that also support captions and linking images in Plone, 
Home-page: http://plone.org/products/collective.nivoslider
Author: David Bain
Author-email: pigeonflight@gmail.com
License: GPL
Keywords: plone slideshow lightbox jquery nivoslider
Platform: UNKNOWN
Classifier: Framework :: Plone
Classifier: Programming Language :: Python
Classifier: Programming Language :: JavaScript
Classifier: Development Status :: 4 - Beta
Classifier: Topic :: Software Development :: User Interfaces
